clossh/__init__.py
clossh/control/__init__.py
clossh/control/controller.py
clossh/control/ssh.py
control/__init__.py
control/controller.py
control/ssh.py
tools/__init__.py
tools/auth_cluster.py
clossh-0.0.3.dist-info/LICENSE
clossh-0.0.3.dist-info/METADATA
clossh-0.0.3.dist-info/WHEEL
clossh-0.0.3.dist-info/top_level.txt
clossh-0.0.3.dist-info/RECORD
